<?xml version="1.0" encoding="UTF-8"?>
<mxfile host="app.diagrams.net" agent="Mozilla/5.0 (Windows NT 10.0; Win64; x64) AppleWebKit/537.36 (KHTML, like Gecko) Chrome/133.0.0.0 Safari/537.36 OPR/118.0.0.0" version="27.0.4">
  <diagram name="Page-1" id="V0ptsHWJ5Blz7RSVZ5B2">
    <mxGraphModel dx="2829" dy="1306" grid="1" gridSize="10" guides="1" tooltips="1" connect="1" arrows="1" fold="1" page="1" pageScale="1" pageWidth="827" pageHeight="1169" math="0" shadow="0">
      <root>
        <mxCell id="0" />
        <mxCell id="1" parent="0" />
        <mxCell id="oWGjtTSNWEf_jc8DIcA6-1" value="" style="shape=mxgraph.cisco.routers.router;sketch=0;html=1;pointerEvents=1;dashed=0;fillColor=#036897;strokeColor=#ffffff;strokeWidth=2;verticalLabelPosition=bottom;verticalAlign=top;align=center;outlineConnect=0;" parent="1" vertex="1">
          <mxGeometry x="250" y="200" width="78" height="53" as="geometry" />
        </mxCell>
        <mxCell id="oWGjtTSNWEf_jc8DIcA6-3" value="" style="shape=mxgraph.cisco.routers.router;sketch=0;html=1;pointerEvents=1;dashed=0;fillColor=#036897;strokeColor=#ffffff;strokeWidth=2;verticalLabelPosition=bottom;verticalAlign=top;align=center;outlineConnect=0;" parent="1" vertex="1">
          <mxGeometry x="1343" y="200" width="78" height="53" as="geometry" />
        </mxCell>
        <mxCell id="oWGjtTSNWEf_jc8DIcA6-4" value="" style="shape=mxgraph.cisco.security.firewall;html=1;pointerEvents=1;dashed=0;fillColor=#036897;strokeColor=#ffffff;strokeWidth=2;verticalLabelPosition=bottom;verticalAlign=top;align=center;outlineConnect=0;" parent="1" vertex="1">
          <mxGeometry x="269" y="338.5" width="29" height="67" as="geometry" />
        </mxCell>
        <mxCell id="oWGjtTSNWEf_jc8DIcA6-6" value="" style="shape=mxgraph.cisco.switches.layer_3_switch;sketch=0;html=1;pointerEvents=1;dashed=0;fillColor=#036897;strokeColor=#ffffff;strokeWidth=2;verticalLabelPosition=bottom;verticalAlign=top;align=center;outlineConnect=0;" parent="1" vertex="1">
          <mxGeometry x="258" y="585" width="64" height="64" as="geometry" />
        </mxCell>
        <mxCell id="oWGjtTSNWEf_jc8DIcA6-7" value="" style="shape=mxgraph.cisco.switches.workgroup_switch;sketch=0;html=1;pointerEvents=1;dashed=0;fillColor=#036897;strokeColor=#ffffff;strokeWidth=2;verticalLabelPosition=bottom;verticalAlign=top;align=center;outlineConnect=0;" parent="1" vertex="1">
          <mxGeometry x="50" y="550" width="101" height="50" as="geometry" />
        </mxCell>
        <mxCell id="oWGjtTSNWEf_jc8DIcA6-8" value="" style="shape=mxgraph.cisco.switches.workgroup_switch;sketch=0;html=1;pointerEvents=1;dashed=0;fillColor=#036897;strokeColor=#ffffff;strokeWidth=2;verticalLabelPosition=bottom;verticalAlign=top;align=center;outlineConnect=0;" parent="1" vertex="1">
          <mxGeometry x="414" y="550" width="101" height="50" as="geometry" />
        </mxCell>
        <mxCell id="oWGjtTSNWEf_jc8DIcA6-9" value="" style="shape=mxgraph.cisco.switches.workgroup_switch;sketch=0;html=1;pointerEvents=1;dashed=0;fillColor=#036897;strokeColor=#ffffff;strokeWidth=2;verticalLabelPosition=bottom;verticalAlign=top;align=center;outlineConnect=0;" parent="1" vertex="1">
          <mxGeometry x="-101" y="720" width="101" height="50" as="geometry" />
        </mxCell>
        <mxCell id="oWGjtTSNWEf_jc8DIcA6-10" value="" style="shape=mxgraph.cisco.switches.workgroup_switch;sketch=0;html=1;pointerEvents=1;dashed=0;fillColor=#036897;strokeColor=#ffffff;strokeWidth=2;verticalLabelPosition=bottom;verticalAlign=top;align=center;outlineConnect=0;" parent="1" vertex="1">
          <mxGeometry x="540" y="720" width="101" height="50" as="geometry" />
        </mxCell>
        <mxCell id="oWGjtTSNWEf_jc8DIcA6-11" value="" style="shape=mxgraph.cisco.switches.workgroup_switch;sketch=0;html=1;pointerEvents=1;dashed=0;fillColor=#036897;strokeColor=#ffffff;strokeWidth=2;verticalLabelPosition=bottom;verticalAlign=top;align=center;outlineConnect=0;" parent="1" vertex="1">
          <mxGeometry x="240" y="950" width="101" height="50" as="geometry" />
        </mxCell>
        <mxCell id="oWGjtTSNWEf_jc8DIcA6-12" value="" style="shape=mxgraph.cisco.servers.fileserver;sketch=0;html=1;pointerEvents=1;dashed=0;fillColor=#036897;strokeColor=#ffffff;strokeWidth=2;verticalLabelPosition=bottom;verticalAlign=top;align=center;outlineConnect=0;" parent="1" vertex="1">
          <mxGeometry x="130" y="1040" width="43" height="62" as="geometry" />
        </mxCell>
        <mxCell id="oWGjtTSNWEf_jc8DIcA6-13" value="" style="shape=mxgraph.cisco.servers.fileserver;sketch=0;html=1;pointerEvents=1;dashed=0;fillColor=#036897;strokeColor=#ffffff;strokeWidth=2;verticalLabelPosition=bottom;verticalAlign=top;align=center;outlineConnect=0;" parent="1" vertex="1">
          <mxGeometry x="269" y="1080" width="43" height="62" as="geometry" />
        </mxCell>
        <mxCell id="oWGjtTSNWEf_jc8DIcA6-14" value="" style="shape=mxgraph.cisco.servers.fileserver;sketch=0;html=1;pointerEvents=1;dashed=0;fillColor=#036897;strokeColor=#ffffff;strokeWidth=2;verticalLabelPosition=bottom;verticalAlign=top;align=center;outlineConnect=0;" parent="1" vertex="1">
          <mxGeometry x="410" y="1040" width="43" height="62" as="geometry" />
        </mxCell>
        <mxCell id="oWGjtTSNWEf_jc8DIcA6-15" value="" style="shape=mxgraph.cisco.switches.workgroup_switch;sketch=0;html=1;pointerEvents=1;dashed=0;fillColor=#036897;strokeColor=#ffffff;strokeWidth=2;verticalLabelPosition=bottom;verticalAlign=top;align=center;outlineConnect=0;" parent="1" vertex="1">
          <mxGeometry x="80" y="347" width="101" height="50" as="geometry" />
        </mxCell>
        <mxCell id="oWGjtTSNWEf_jc8DIcA6-16" value="" style="shape=mxgraph.cisco.servers.fileserver;sketch=0;html=1;pointerEvents=1;dashed=0;fillColor=#036897;strokeColor=#ffffff;strokeWidth=2;verticalLabelPosition=bottom;verticalAlign=top;align=center;outlineConnect=0;" parent="1" vertex="1">
          <mxGeometry x="-50" y="397" width="43" height="62" as="geometry" />
        </mxCell>
        <mxCell id="oWGjtTSNWEf_jc8DIcA6-17" value="" style="shape=mxgraph.cisco.servers.fileserver;sketch=0;html=1;pointerEvents=1;dashed=0;fillColor=#036897;strokeColor=#ffffff;strokeWidth=2;verticalLabelPosition=bottom;verticalAlign=top;align=center;outlineConnect=0;" parent="1" vertex="1">
          <mxGeometry x="-50" y="285" width="43" height="62" as="geometry" />
        </mxCell>
        <mxCell id="oWGjtTSNWEf_jc8DIcA6-18" value="" style="shape=mxgraph.cisco.misc.access_point;sketch=0;html=1;pointerEvents=1;dashed=0;fillColor=#036897;strokeColor=#ffffff;strokeWidth=2;verticalLabelPosition=bottom;verticalAlign=top;align=center;outlineConnect=0;" parent="1" vertex="1">
          <mxGeometry x="540" y="459" width="75" height="34" as="geometry" />
        </mxCell>
        <mxCell id="oWGjtTSNWEf_jc8DIcA6-19" value="" style="shape=mxgraph.cisco.computers_and_peripherals.video_camera;sketch=0;html=1;pointerEvents=1;dashed=0;fillColor=#036897;strokeColor=#ffffff;strokeWidth=2;verticalLabelPosition=bottom;verticalAlign=top;align=center;outlineConnect=0;" parent="1" vertex="1">
          <mxGeometry x="574" y="323" width="67" height="98" as="geometry" />
        </mxCell>
        <mxCell id="oWGjtTSNWEf_jc8DIcA6-20" value="" style="shape=mxgraph.cisco.computers_and_peripherals.video_camera;sketch=0;html=1;pointerEvents=1;dashed=0;fillColor=#036897;strokeColor=#ffffff;strokeWidth=2;verticalLabelPosition=bottom;verticalAlign=top;align=center;outlineConnect=0;" parent="1" vertex="1">
          <mxGeometry x="660" y="361" width="67" height="98" as="geometry" />
        </mxCell>
        <mxCell id="oWGjtTSNWEf_jc8DIcA6-21" value="" style="shape=mxgraph.cisco.computers_and_peripherals.video_camera;sketch=0;html=1;pointerEvents=1;dashed=0;fillColor=#036897;strokeColor=#ffffff;strokeWidth=2;verticalLabelPosition=bottom;verticalAlign=top;align=center;outlineConnect=0;" parent="1" vertex="1">
          <mxGeometry x="641" y="477" width="67" height="98" as="geometry" />
        </mxCell>
        <mxCell id="oWGjtTSNWEf_jc8DIcA6-23" value="" style="endArrow=none;dashed=1;html=1;rounded=0;" parent="1" source="oWGjtTSNWEf_jc8DIcA6-6" target="oWGjtTSNWEf_jc8DIcA6-8" edge="1">
          <mxGeometry width="50" height="50" relative="1" as="geometry">
            <mxPoint x="270" y="860" as="sourcePoint" />
            <mxPoint x="320" y="810" as="targetPoint" />
          </mxGeometry>
        </mxCell>
        <mxCell id="oWGjtTSNWEf_jc8DIcA6-24" value="" style="endArrow=none;dashed=1;html=1;rounded=0;" parent="1" source="oWGjtTSNWEf_jc8DIcA6-6" target="oWGjtTSNWEf_jc8DIcA6-7" edge="1">
          <mxGeometry width="50" height="50" relative="1" as="geometry">
            <mxPoint x="280" y="870" as="sourcePoint" />
            <mxPoint x="330" y="820" as="targetPoint" />
          </mxGeometry>
        </mxCell>
        <mxCell id="oWGjtTSNWEf_jc8DIcA6-25" value="" style="endArrow=none;dashed=1;html=1;rounded=0;" parent="1" source="oWGjtTSNWEf_jc8DIcA6-9" target="oWGjtTSNWEf_jc8DIcA6-7" edge="1">
          <mxGeometry width="50" height="50" relative="1" as="geometry">
            <mxPoint x="290" y="880" as="sourcePoint" />
            <mxPoint x="340" y="830" as="targetPoint" />
          </mxGeometry>
        </mxCell>
        <mxCell id="oWGjtTSNWEf_jc8DIcA6-26" value="" style="endArrow=none;dashed=1;html=1;rounded=0;" parent="1" source="oWGjtTSNWEf_jc8DIcA6-11" target="oWGjtTSNWEf_jc8DIcA6-9" edge="1">
          <mxGeometry width="50" height="50" relative="1" as="geometry">
            <mxPoint x="300" y="890" as="sourcePoint" />
            <mxPoint x="350" y="840" as="targetPoint" />
          </mxGeometry>
        </mxCell>
        <mxCell id="oWGjtTSNWEf_jc8DIcA6-27" value="" style="endArrow=none;dashed=1;html=1;rounded=0;" parent="1" source="oWGjtTSNWEf_jc8DIcA6-11" target="oWGjtTSNWEf_jc8DIcA6-10" edge="1">
          <mxGeometry width="50" height="50" relative="1" as="geometry">
            <mxPoint x="310" y="900" as="sourcePoint" />
            <mxPoint x="360" y="850" as="targetPoint" />
          </mxGeometry>
        </mxCell>
        <mxCell id="oWGjtTSNWEf_jc8DIcA6-28" value="" style="endArrow=none;dashed=1;html=1;rounded=0;" parent="1" source="oWGjtTSNWEf_jc8DIcA6-11" target="oWGjtTSNWEf_jc8DIcA6-6" edge="1">
          <mxGeometry width="50" height="50" relative="1" as="geometry">
            <mxPoint x="270" y="860" as="sourcePoint" />
            <mxPoint x="320" y="810" as="targetPoint" />
          </mxGeometry>
        </mxCell>
        <mxCell id="oWGjtTSNWEf_jc8DIcA6-29" value="" style="endArrow=none;dashed=1;html=1;rounded=0;" parent="1" source="oWGjtTSNWEf_jc8DIcA6-11" target="oWGjtTSNWEf_jc8DIcA6-7" edge="1">
          <mxGeometry width="50" height="50" relative="1" as="geometry">
            <mxPoint x="280" y="870" as="sourcePoint" />
            <mxPoint x="330" y="820" as="targetPoint" />
          </mxGeometry>
        </mxCell>
        <mxCell id="oWGjtTSNWEf_jc8DIcA6-30" value="" style="endArrow=none;dashed=1;html=1;rounded=0;" parent="1" source="oWGjtTSNWEf_jc8DIcA6-11" target="oWGjtTSNWEf_jc8DIcA6-8" edge="1">
          <mxGeometry width="50" height="50" relative="1" as="geometry">
            <mxPoint x="290" y="880" as="sourcePoint" />
            <mxPoint x="340" y="830" as="targetPoint" />
          </mxGeometry>
        </mxCell>
        <mxCell id="oWGjtTSNWEf_jc8DIcA6-31" value="" style="endArrow=none;dashed=1;html=1;rounded=0;" parent="1" source="oWGjtTSNWEf_jc8DIcA6-10" target="oWGjtTSNWEf_jc8DIcA6-8" edge="1">
          <mxGeometry width="50" height="50" relative="1" as="geometry">
            <mxPoint x="300" y="890" as="sourcePoint" />
            <mxPoint x="350" y="840" as="targetPoint" />
          </mxGeometry>
        </mxCell>
        <mxCell id="oWGjtTSNWEf_jc8DIcA6-32" value="" style="endArrow=none;html=1;rounded=0;" parent="1" edge="1" target="FF6CjetviQNnHgp1nNf3-21" source="FF6CjetviQNnHgp1nNf3-10">
          <mxGeometry width="50" height="50" relative="1" as="geometry">
            <mxPoint x="1563" y="1298" as="sourcePoint" />
            <mxPoint x="1613" y="1248" as="targetPoint" />
          </mxGeometry>
        </mxCell>
        <mxCell id="oWGjtTSNWEf_jc8DIcA6-33" value="" style="endArrow=none;html=1;rounded=0;" parent="1" source="oWGjtTSNWEf_jc8DIcA6-14" target="oWGjtTSNWEf_jc8DIcA6-11" edge="1">
          <mxGeometry width="50" height="50" relative="1" as="geometry">
            <mxPoint x="40" y="1030" as="sourcePoint" />
            <mxPoint x="90" y="980" as="targetPoint" />
          </mxGeometry>
        </mxCell>
        <mxCell id="oWGjtTSNWEf_jc8DIcA6-34" value="" style="endArrow=none;html=1;rounded=0;" parent="1" source="oWGjtTSNWEf_jc8DIcA6-13" target="oWGjtTSNWEf_jc8DIcA6-11" edge="1">
          <mxGeometry width="50" height="50" relative="1" as="geometry">
            <mxPoint x="50" y="1040" as="sourcePoint" />
            <mxPoint x="100" y="990" as="targetPoint" />
          </mxGeometry>
        </mxCell>
        <mxCell id="oWGjtTSNWEf_jc8DIcA6-35" value="" style="endArrow=none;html=1;rounded=0;" parent="1" source="oWGjtTSNWEf_jc8DIcA6-12" target="oWGjtTSNWEf_jc8DIcA6-11" edge="1">
          <mxGeometry width="50" height="50" relative="1" as="geometry">
            <mxPoint x="60" y="1050" as="sourcePoint" />
            <mxPoint x="110" y="1000" as="targetPoint" />
          </mxGeometry>
        </mxCell>
        <mxCell id="oWGjtTSNWEf_jc8DIcA6-36" value="" style="endArrow=none;dashed=1;html=1;rounded=0;" parent="1" source="oWGjtTSNWEf_jc8DIcA6-4" target="oWGjtTSNWEf_jc8DIcA6-1" edge="1">
          <mxGeometry width="50" height="50" relative="1" as="geometry">
            <mxPoint x="390" y="511" as="sourcePoint" />
            <mxPoint x="440" y="461" as="targetPoint" />
          </mxGeometry>
        </mxCell>
        <mxCell id="oWGjtTSNWEf_jc8DIcA6-37" value="" style="endArrow=none;dashed=1;html=1;rounded=0;" parent="1" source="oWGjtTSNWEf_jc8DIcA6-4" target="oWGjtTSNWEf_jc8DIcA6-15" edge="1">
          <mxGeometry width="50" height="50" relative="1" as="geometry">
            <mxPoint x="400" y="521" as="sourcePoint" />
            <mxPoint x="450" y="471" as="targetPoint" />
          </mxGeometry>
        </mxCell>
        <mxCell id="oWGjtTSNWEf_jc8DIcA6-38" value="" style="endArrow=none;dashed=1;html=1;rounded=0;" parent="1" source="oWGjtTSNWEf_jc8DIcA6-6" target="oWGjtTSNWEf_jc8DIcA6-4" edge="1">
          <mxGeometry width="50" height="50" relative="1" as="geometry">
            <mxPoint x="410" y="531" as="sourcePoint" />
            <mxPoint x="460" y="481" as="targetPoint" />
          </mxGeometry>
        </mxCell>
        <mxCell id="oWGjtTSNWEf_jc8DIcA6-39" value="" style="endArrow=none;html=1;rounded=0;" parent="1" source="oWGjtTSNWEf_jc8DIcA6-8" target="oWGjtTSNWEf_jc8DIcA6-18" edge="1">
          <mxGeometry width="50" height="50" relative="1" as="geometry">
            <mxPoint x="460" y="510" as="sourcePoint" />
            <mxPoint x="510" y="460" as="targetPoint" />
          </mxGeometry>
        </mxCell>
        <mxCell id="oWGjtTSNWEf_jc8DIcA6-40" value="" style="endArrow=none;html=1;rounded=0;" parent="1" source="oWGjtTSNWEf_jc8DIcA6-15" target="oWGjtTSNWEf_jc8DIcA6-16" edge="1">
          <mxGeometry width="50" height="50" relative="1" as="geometry">
            <mxPoint x="-43.5" y="553" as="sourcePoint" />
            <mxPoint x="6.5" y="503" as="targetPoint" />
          </mxGeometry>
        </mxCell>
        <mxCell id="oWGjtTSNWEf_jc8DIcA6-41" value="" style="endArrow=none;html=1;rounded=0;" parent="1" source="oWGjtTSNWEf_jc8DIcA6-15" target="oWGjtTSNWEf_jc8DIcA6-17" edge="1">
          <mxGeometry width="50" height="50" relative="1" as="geometry">
            <mxPoint x="-33.5" y="563" as="sourcePoint" />
            <mxPoint x="16.5" y="513" as="targetPoint" />
          </mxGeometry>
        </mxCell>
        <mxCell id="oWGjtTSNWEf_jc8DIcA6-42" value="" style="curved=1;endArrow=classic;html=1;rounded=0;" parent="1" source="oWGjtTSNWEf_jc8DIcA6-1" target="oWGjtTSNWEf_jc8DIcA6-3" edge="1">
          <mxGeometry width="50" height="50" relative="1" as="geometry">
            <mxPoint x="490" y="190" as="sourcePoint" />
            <mxPoint x="540" y="140" as="targetPoint" />
            <Array as="points">
              <mxPoint x="550" y="280" />
              <mxPoint x="770" y="110" />
            </Array>
          </mxGeometry>
        </mxCell>
        <mxCell id="oWGjtTSNWEf_jc8DIcA6-43" value="" style="endArrow=none;dashed=1;html=1;rounded=0;" parent="1" source="oWGjtTSNWEf_jc8DIcA6-48" target="oWGjtTSNWEf_jc8DIcA6-49" edge="1">
          <mxGeometry width="50" height="50" relative="1" as="geometry">
            <mxPoint x="1243" y="371" as="sourcePoint" />
            <mxPoint x="1293" y="321" as="targetPoint" />
          </mxGeometry>
        </mxCell>
        <mxCell id="oWGjtTSNWEf_jc8DIcA6-44" value="" style="endArrow=none;dashed=1;html=1;rounded=0;" parent="1" source="oWGjtTSNWEf_jc8DIcA6-48" target="oWGjtTSNWEf_jc8DIcA6-46" edge="1">
          <mxGeometry width="50" height="50" relative="1" as="geometry">
            <mxPoint x="1253" y="381" as="sourcePoint" />
            <mxPoint x="1303" y="331" as="targetPoint" />
          </mxGeometry>
        </mxCell>
        <mxCell id="oWGjtTSNWEf_jc8DIcA6-45" value="" style="endArrow=none;dashed=1;html=1;rounded=0;" parent="1" source="oWGjtTSNWEf_jc8DIcA6-46" target="oWGjtTSNWEf_jc8DIcA6-3" edge="1">
          <mxGeometry width="50" height="50" relative="1" as="geometry">
            <mxPoint x="1220" y="380" as="sourcePoint" />
            <mxPoint x="1160" y="353" as="targetPoint" />
          </mxGeometry>
        </mxCell>
        <mxCell id="oWGjtTSNWEf_jc8DIcA6-46" value="" style="shape=mxgraph.cisco.security.firewall;html=1;pointerEvents=1;dashed=0;fillColor=#036897;strokeColor=#ffffff;strokeWidth=2;verticalLabelPosition=bottom;verticalAlign=top;align=center;outlineConnect=0;" parent="1" vertex="1">
          <mxGeometry x="1367.5" y="342" width="29" height="67" as="geometry" />
        </mxCell>
        <mxCell id="oWGjtTSNWEf_jc8DIcA6-48" value="" style="shape=mxgraph.cisco.switches.workgroup_switch;sketch=0;html=1;pointerEvents=1;dashed=0;fillColor=#036897;strokeColor=#ffffff;strokeWidth=2;verticalLabelPosition=bottom;verticalAlign=top;align=center;outlineConnect=0;" parent="1" vertex="1">
          <mxGeometry x="1331.5" y="488" width="101" height="50" as="geometry" />
        </mxCell>
        <mxCell id="oWGjtTSNWEf_jc8DIcA6-49" value="" style="shape=mxgraph.cisco.security.firewall;html=1;pointerEvents=1;dashed=0;fillColor=#036897;strokeColor=#ffffff;strokeWidth=2;verticalLabelPosition=bottom;verticalAlign=top;align=center;outlineConnect=0;" parent="1" vertex="1">
          <mxGeometry x="1367.5" y="641" width="29" height="67" as="geometry" />
        </mxCell>
        <mxCell id="oWGjtTSNWEf_jc8DIcA6-50" value="" style="shape=mxgraph.cisco.servers.fileserver;sketch=0;html=1;pointerEvents=1;dashed=0;fillColor=#036897;strokeColor=#ffffff;strokeWidth=2;verticalLabelPosition=bottom;verticalAlign=top;align=center;outlineConnect=0;" parent="1" vertex="1">
          <mxGeometry x="1533" y="526" width="43" height="62" as="geometry" />
        </mxCell>
        <mxCell id="oWGjtTSNWEf_jc8DIcA6-51" value="" style="shape=mxgraph.cisco.servers.fileserver;sketch=0;html=1;pointerEvents=1;dashed=0;fillColor=#036897;strokeColor=#ffffff;strokeWidth=2;verticalLabelPosition=bottom;verticalAlign=top;align=center;outlineConnect=0;" parent="1" vertex="1">
          <mxGeometry x="1533" y="409" width="43" height="62" as="geometry" />
        </mxCell>
        <mxCell id="oWGjtTSNWEf_jc8DIcA6-52" value="" style="endArrow=none;html=1;rounded=0;" parent="1" source="oWGjtTSNWEf_jc8DIcA6-51" target="oWGjtTSNWEf_jc8DIcA6-48" edge="1">
          <mxGeometry width="50" height="50" relative="1" as="geometry">
            <mxPoint x="1183" y="618" as="sourcePoint" />
            <mxPoint x="1233" y="568" as="targetPoint" />
          </mxGeometry>
        </mxCell>
        <mxCell id="oWGjtTSNWEf_jc8DIcA6-53" value="" style="endArrow=none;html=1;rounded=0;" parent="1" source="oWGjtTSNWEf_jc8DIcA6-50" target="oWGjtTSNWEf_jc8DIcA6-48" edge="1">
          <mxGeometry width="50" height="50" relative="1" as="geometry">
            <mxPoint x="1193" y="628" as="sourcePoint" />
            <mxPoint x="1243" y="578" as="targetPoint" />
          </mxGeometry>
        </mxCell>
        <mxCell id="oWGjtTSNWEf_jc8DIcA6-54" value="" style="endArrow=none;dashed=1;html=1;rounded=0;" parent="1" source="FF6CjetviQNnHgp1nNf3-5" target="oWGjtTSNWEf_jc8DIcA6-49" edge="1">
          <mxGeometry width="50" height="50" relative="1" as="geometry">
            <mxPoint x="1382" y="858" as="sourcePoint" />
            <mxPoint x="1293" y="321" as="targetPoint" />
          </mxGeometry>
        </mxCell>
        <mxCell id="FF6CjetviQNnHgp1nNf3-1" value="" style="endArrow=none;dashed=1;html=1;dashPattern=1 3;strokeWidth=2;rounded=0;" edge="1" parent="1" source="FF6CjetviQNnHgp1nNf3-61" target="FF6CjetviQNnHgp1nNf3-64">
          <mxGeometry width="50" height="50" relative="1" as="geometry">
            <mxPoint x="1243" y="798" as="sourcePoint" />
            <mxPoint x="1953" y="888" as="targetPoint" />
          </mxGeometry>
        </mxCell>
        <mxCell id="FF6CjetviQNnHgp1nNf3-2" value="" style="endArrow=none;dashed=1;html=1;dashPattern=1 3;strokeWidth=2;rounded=0;" edge="1" parent="1" source="oWGjtTSNWEf_jc8DIcA6-18" target="oWGjtTSNWEf_jc8DIcA6-21">
          <mxGeometry width="50" height="50" relative="1" as="geometry">
            <mxPoint x="340" y="760" as="sourcePoint" />
            <mxPoint x="390" y="710" as="targetPoint" />
          </mxGeometry>
        </mxCell>
        <mxCell id="FF6CjetviQNnHgp1nNf3-3" value="" style="endArrow=none;dashed=1;html=1;dashPattern=1 3;strokeWidth=2;rounded=0;" edge="1" parent="1" source="oWGjtTSNWEf_jc8DIcA6-18" target="oWGjtTSNWEf_jc8DIcA6-20">
          <mxGeometry width="50" height="50" relative="1" as="geometry">
            <mxPoint x="350" y="770" as="sourcePoint" />
            <mxPoint x="400" y="720" as="targetPoint" />
          </mxGeometry>
        </mxCell>
        <mxCell id="FF6CjetviQNnHgp1nNf3-4" value="" style="endArrow=none;dashed=1;html=1;dashPattern=1 3;strokeWidth=2;rounded=0;" edge="1" parent="1" source="oWGjtTSNWEf_jc8DIcA6-18" target="oWGjtTSNWEf_jc8DIcA6-19">
          <mxGeometry width="50" height="50" relative="1" as="geometry">
            <mxPoint x="360" y="780" as="sourcePoint" />
            <mxPoint x="410" y="730" as="targetPoint" />
          </mxGeometry>
        </mxCell>
        <mxCell id="FF6CjetviQNnHgp1nNf3-5" value="" style="shape=mxgraph.cisco.switches.layer_3_switch;sketch=0;html=1;pointerEvents=1;dashed=0;fillColor=#036897;strokeColor=#ffffff;strokeWidth=2;verticalLabelPosition=bottom;verticalAlign=top;align=center;outlineConnect=0;" vertex="1" parent="1">
          <mxGeometry x="1350" y="858" width="64" height="64" as="geometry" />
        </mxCell>
        <mxCell id="FF6CjetviQNnHgp1nNf3-6" value="" style="shape=mxgraph.cisco.switches.workgroup_switch;sketch=0;html=1;pointerEvents=1;dashed=0;fillColor=#036897;strokeColor=#ffffff;strokeWidth=2;verticalLabelPosition=bottom;verticalAlign=top;align=center;outlineConnect=0;" vertex="1" parent="1">
          <mxGeometry x="1331.5" y="1118" width="101" height="50" as="geometry" />
        </mxCell>
        <mxCell id="FF6CjetviQNnHgp1nNf3-7" value="" style="shape=mxgraph.cisco.switches.workgroup_switch;sketch=0;html=1;pointerEvents=1;dashed=0;fillColor=#036897;strokeColor=#ffffff;strokeWidth=2;verticalLabelPosition=bottom;verticalAlign=top;align=center;outlineConnect=0;" vertex="1" parent="1">
          <mxGeometry x="1643" y="865" width="101" height="50" as="geometry" />
        </mxCell>
        <mxCell id="FF6CjetviQNnHgp1nNf3-8" value="" style="shape=mxgraph.cisco.switches.workgroup_switch;sketch=0;html=1;pointerEvents=1;dashed=0;fillColor=#036897;strokeColor=#ffffff;strokeWidth=2;verticalLabelPosition=bottom;verticalAlign=top;align=center;outlineConnect=0;" vertex="1" parent="1">
          <mxGeometry x="1003" y="865" width="101" height="50" as="geometry" />
        </mxCell>
        <mxCell id="FF6CjetviQNnHgp1nNf3-9" value="" style="shape=mxgraph.cisco.switches.workgroup_switch;sketch=0;html=1;pointerEvents=1;dashed=0;fillColor=#036897;strokeColor=#ffffff;strokeWidth=2;verticalLabelPosition=bottom;verticalAlign=top;align=center;outlineConnect=0;" vertex="1" parent="1">
          <mxGeometry x="1003" y="1118" width="101" height="50" as="geometry" />
        </mxCell>
        <mxCell id="FF6CjetviQNnHgp1nNf3-10" value="" style="shape=mxgraph.cisco.switches.workgroup_switch;sketch=0;html=1;pointerEvents=1;dashed=0;fillColor=#036897;strokeColor=#ffffff;strokeWidth=2;verticalLabelPosition=bottom;verticalAlign=top;align=center;outlineConnect=0;" vertex="1" parent="1">
          <mxGeometry x="1331.5" y="1368" width="101" height="50" as="geometry" />
        </mxCell>
        <mxCell id="FF6CjetviQNnHgp1nNf3-11" value="" style="endArrow=none;dashed=1;html=1;rounded=0;" edge="1" parent="1" source="FF6CjetviQNnHgp1nNf3-6" target="FF6CjetviQNnHgp1nNf3-5">
          <mxGeometry width="50" height="50" relative="1" as="geometry">
            <mxPoint x="1243" y="371" as="sourcePoint" />
            <mxPoint x="1293" y="321" as="targetPoint" />
          </mxGeometry>
        </mxCell>
        <mxCell id="FF6CjetviQNnHgp1nNf3-12" value="" style="endArrow=none;dashed=1;html=1;rounded=0;" edge="1" parent="1" source="FF6CjetviQNnHgp1nNf3-5" target="FF6CjetviQNnHgp1nNf3-7">
          <mxGeometry width="50" height="50" relative="1" as="geometry">
            <mxPoint x="1253" y="381" as="sourcePoint" />
            <mxPoint x="1303" y="331" as="targetPoint" />
          </mxGeometry>
        </mxCell>
        <mxCell id="FF6CjetviQNnHgp1nNf3-13" value="" style="endArrow=none;dashed=1;html=1;rounded=0;" edge="1" parent="1" source="FF6CjetviQNnHgp1nNf3-8" target="FF6CjetviQNnHgp1nNf3-5">
          <mxGeometry width="50" height="50" relative="1" as="geometry">
            <mxPoint x="1263" y="391" as="sourcePoint" />
            <mxPoint x="1313" y="341" as="targetPoint" />
          </mxGeometry>
        </mxCell>
        <mxCell id="FF6CjetviQNnHgp1nNf3-14" value="" style="endArrow=none;dashed=1;html=1;rounded=0;" edge="1" parent="1" source="FF6CjetviQNnHgp1nNf3-9" target="FF6CjetviQNnHgp1nNf3-6">
          <mxGeometry width="50" height="50" relative="1" as="geometry">
            <mxPoint x="1273" y="401" as="sourcePoint" />
            <mxPoint x="1323" y="351" as="targetPoint" />
          </mxGeometry>
        </mxCell>
        <mxCell id="FF6CjetviQNnHgp1nNf3-15" value="" style="endArrow=none;dashed=1;html=1;rounded=0;" edge="1" parent="1" source="FF6CjetviQNnHgp1nNf3-6" target="FF6CjetviQNnHgp1nNf3-10">
          <mxGeometry width="50" height="50" relative="1" as="geometry">
            <mxPoint x="1243" y="371" as="sourcePoint" />
            <mxPoint x="1293" y="321" as="targetPoint" />
          </mxGeometry>
        </mxCell>
        <mxCell id="FF6CjetviQNnHgp1nNf3-16" value="" style="shape=mxgraph.cisco.computers_and_peripherals.pc;sketch=0;html=1;pointerEvents=1;dashed=0;fillColor=#036897;strokeColor=#ffffff;strokeWidth=2;verticalLabelPosition=bottom;verticalAlign=top;align=center;outlineConnect=0;" vertex="1" parent="1">
          <mxGeometry x="873" y="898" width="78" height="70" as="geometry" />
        </mxCell>
        <mxCell id="FF6CjetviQNnHgp1nNf3-17" value="" style="shape=mxgraph.cisco.computers_and_peripherals.pc;sketch=0;html=1;pointerEvents=1;dashed=0;fillColor=#036897;strokeColor=#ffffff;strokeWidth=2;verticalLabelPosition=bottom;verticalAlign=top;align=center;outlineConnect=0;" vertex="1" parent="1">
          <mxGeometry x="861" y="808" width="78" height="70" as="geometry" />
        </mxCell>
        <mxCell id="FF6CjetviQNnHgp1nNf3-18" value="" style="shape=mxgraph.cisco.computers_and_peripherals.pc;sketch=0;html=1;pointerEvents=1;dashed=0;fillColor=#036897;strokeColor=#ffffff;strokeWidth=2;verticalLabelPosition=bottom;verticalAlign=top;align=center;outlineConnect=0;" vertex="1" parent="1">
          <mxGeometry x="973" y="728" width="78" height="70" as="geometry" />
        </mxCell>
        <mxCell id="FF6CjetviQNnHgp1nNf3-19" value="" style="shape=mxgraph.cisco.computers_and_peripherals.pc;sketch=0;html=1;pointerEvents=1;dashed=0;fillColor=#036897;strokeColor=#ffffff;strokeWidth=2;verticalLabelPosition=bottom;verticalAlign=top;align=center;outlineConnect=0;" vertex="1" parent="1">
          <mxGeometry x="1215" y="1448" width="78" height="70" as="geometry" />
        </mxCell>
        <mxCell id="FF6CjetviQNnHgp1nNf3-20" value="" style="shape=mxgraph.cisco.computers_and_peripherals.pc;sketch=0;html=1;pointerEvents=1;dashed=0;fillColor=#036897;strokeColor=#ffffff;strokeWidth=2;verticalLabelPosition=bottom;verticalAlign=top;align=center;outlineConnect=0;" vertex="1" parent="1">
          <mxGeometry x="1293" y="1508" width="78" height="70" as="geometry" />
        </mxCell>
        <mxCell id="FF6CjetviQNnHgp1nNf3-21" value="" style="shape=mxgraph.cisco.computers_and_peripherals.pc;sketch=0;html=1;pointerEvents=1;dashed=0;fillColor=#036897;strokeColor=#ffffff;strokeWidth=2;verticalLabelPosition=bottom;verticalAlign=top;align=center;outlineConnect=0;" vertex="1" parent="1">
          <mxGeometry x="1396.5" y="1508" width="78" height="70" as="geometry" />
        </mxCell>
        <mxCell id="FF6CjetviQNnHgp1nNf3-22" value="" style="shape=mxgraph.cisco.computers_and_peripherals.pc;sketch=0;html=1;pointerEvents=1;dashed=0;fillColor=#036897;strokeColor=#ffffff;strokeWidth=2;verticalLabelPosition=bottom;verticalAlign=top;align=center;outlineConnect=0;" vertex="1" parent="1">
          <mxGeometry x="1498" y="1448" width="78" height="70" as="geometry" />
        </mxCell>
        <mxCell id="FF6CjetviQNnHgp1nNf3-23" value="" style="shape=mxgraph.cisco.modems_and_phones.ip_phone;html=1;pointerEvents=1;dashed=0;fillColor=#036897;strokeColor=#ffffff;strokeWidth=2;verticalLabelPosition=bottom;verticalAlign=top;align=center;outlineConnect=0;" vertex="1" parent="1">
          <mxGeometry x="1125" y="1368" width="90" height="50" as="geometry" />
        </mxCell>
        <mxCell id="FF6CjetviQNnHgp1nNf3-24" value="" style="endArrow=none;html=1;rounded=0;" edge="1" parent="1" source="FF6CjetviQNnHgp1nNf3-10" target="FF6CjetviQNnHgp1nNf3-22">
          <mxGeometry width="50" height="50" relative="1" as="geometry">
            <mxPoint x="1474.5" y="1268" as="sourcePoint" />
            <mxPoint x="1524.5" y="1218" as="targetPoint" />
          </mxGeometry>
        </mxCell>
        <mxCell id="FF6CjetviQNnHgp1nNf3-26" value="" style="endArrow=none;html=1;rounded=0;" edge="1" parent="1" source="FF6CjetviQNnHgp1nNf3-23" target="FF6CjetviQNnHgp1nNf3-10">
          <mxGeometry width="50" height="50" relative="1" as="geometry">
            <mxPoint x="1203" y="638" as="sourcePoint" />
            <mxPoint x="1253" y="588" as="targetPoint" />
          </mxGeometry>
        </mxCell>
        <mxCell id="FF6CjetviQNnHgp1nNf3-27" value="" style="endArrow=none;html=1;rounded=0;" edge="1" parent="1" source="FF6CjetviQNnHgp1nNf3-8" target="FF6CjetviQNnHgp1nNf3-16">
          <mxGeometry width="50" height="50" relative="1" as="geometry">
            <mxPoint x="1213" y="648" as="sourcePoint" />
            <mxPoint x="1263" y="598" as="targetPoint" />
          </mxGeometry>
        </mxCell>
        <mxCell id="FF6CjetviQNnHgp1nNf3-28" value="" style="endArrow=none;html=1;rounded=0;" edge="1" parent="1" source="FF6CjetviQNnHgp1nNf3-8">
          <mxGeometry width="50" height="50" relative="1" as="geometry">
            <mxPoint x="1223" y="658" as="sourcePoint" />
            <mxPoint x="939" y="854.9413680781759" as="targetPoint" />
          </mxGeometry>
        </mxCell>
        <mxCell id="FF6CjetviQNnHgp1nNf3-29" value="" style="endArrow=none;html=1;rounded=0;" edge="1" parent="1" source="FF6CjetviQNnHgp1nNf3-8" target="FF6CjetviQNnHgp1nNf3-18">
          <mxGeometry width="50" height="50" relative="1" as="geometry">
            <mxPoint x="1233" y="668" as="sourcePoint" />
            <mxPoint x="1283" y="618" as="targetPoint" />
          </mxGeometry>
        </mxCell>
        <mxCell id="FF6CjetviQNnHgp1nNf3-30" value="" style="endArrow=none;html=1;rounded=0;" edge="1" parent="1" source="FF6CjetviQNnHgp1nNf3-37" target="FF6CjetviQNnHgp1nNf3-7">
          <mxGeometry width="50" height="50" relative="1" as="geometry">
            <mxPoint x="1603" y="1118" as="sourcePoint" />
            <mxPoint x="1653" y="1068" as="targetPoint" />
          </mxGeometry>
        </mxCell>
        <mxCell id="FF6CjetviQNnHgp1nNf3-31" value="" style="endArrow=none;html=1;rounded=0;" edge="1" parent="1" source="FF6CjetviQNnHgp1nNf3-36" target="FF6CjetviQNnHgp1nNf3-7">
          <mxGeometry width="50" height="50" relative="1" as="geometry">
            <mxPoint x="1613" y="1128" as="sourcePoint" />
            <mxPoint x="1663" y="1078" as="targetPoint" />
          </mxGeometry>
        </mxCell>
        <mxCell id="FF6CjetviQNnHgp1nNf3-32" value="" style="endArrow=none;html=1;rounded=0;" edge="1" parent="1" source="FF6CjetviQNnHgp1nNf3-19" target="FF6CjetviQNnHgp1nNf3-10">
          <mxGeometry width="50" height="50" relative="1" as="geometry">
            <mxPoint x="1623" y="1138" as="sourcePoint" />
            <mxPoint x="1673" y="1088" as="targetPoint" />
          </mxGeometry>
        </mxCell>
        <mxCell id="FF6CjetviQNnHgp1nNf3-33" value="" style="endArrow=none;html=1;rounded=0;" edge="1" parent="1" source="FF6CjetviQNnHgp1nNf3-10" target="FF6CjetviQNnHgp1nNf3-20">
          <mxGeometry width="50" height="50" relative="1" as="geometry">
            <mxPoint x="1633" y="1148" as="sourcePoint" />
            <mxPoint x="1683" y="1098" as="targetPoint" />
          </mxGeometry>
        </mxCell>
        <mxCell id="FF6CjetviQNnHgp1nNf3-35" value="" style="shape=mxgraph.cisco.computers_and_peripherals.pc;sketch=0;html=1;pointerEvents=1;dashed=0;fillColor=#036897;strokeColor=#ffffff;strokeWidth=2;verticalLabelPosition=bottom;verticalAlign=top;align=center;outlineConnect=0;" vertex="1" parent="1">
          <mxGeometry x="1693" y="948" width="78" height="70" as="geometry" />
        </mxCell>
        <mxCell id="FF6CjetviQNnHgp1nNf3-36" value="" style="shape=mxgraph.cisco.computers_and_peripherals.pc;sketch=0;html=1;pointerEvents=1;dashed=0;fillColor=#036897;strokeColor=#ffffff;strokeWidth=2;verticalLabelPosition=bottom;verticalAlign=top;align=center;outlineConnect=0;" vertex="1" parent="1">
          <mxGeometry x="1763" y="855" width="78" height="70" as="geometry" />
        </mxCell>
        <mxCell id="FF6CjetviQNnHgp1nNf3-37" value="" style="shape=mxgraph.cisco.computers_and_peripherals.pc;sketch=0;html=1;pointerEvents=1;dashed=0;fillColor=#036897;strokeColor=#ffffff;strokeWidth=2;verticalLabelPosition=bottom;verticalAlign=top;align=center;outlineConnect=0;" vertex="1" parent="1">
          <mxGeometry x="1744" y="738" width="78" height="70" as="geometry" />
        </mxCell>
        <mxCell id="FF6CjetviQNnHgp1nNf3-38" value="" style="endArrow=none;html=1;rounded=0;" edge="1" parent="1" source="FF6CjetviQNnHgp1nNf3-35" target="FF6CjetviQNnHgp1nNf3-7">
          <mxGeometry width="50" height="50" relative="1" as="geometry">
            <mxPoint x="1623" y="1138" as="sourcePoint" />
            <mxPoint x="1673" y="1088" as="targetPoint" />
          </mxGeometry>
        </mxCell>
        <mxCell id="FF6CjetviQNnHgp1nNf3-39" value="" style="shape=mxgraph.cisco.hubs_and_gateways.generic_gateway;html=1;pointerEvents=1;dashed=0;fillColor=#036897;strokeColor=#ffffff;strokeWidth=2;verticalLabelPosition=bottom;verticalAlign=top;align=center;outlineConnect=0;" vertex="1" parent="1">
          <mxGeometry x="1522" y="1357" width="66" height="74" as="geometry" />
        </mxCell>
        <mxCell id="FF6CjetviQNnHgp1nNf3-40" value="" style="shape=image;html=1;verticalAlign=top;verticalLabelPosition=bottom;labelBackgroundColor=#ffffff;imageAspect=0;aspect=fixed;image=https://cdn4.iconfinder.com/data/icons/crime-and-security-24/64/7-128.png" vertex="1" parent="1">
          <mxGeometry x="1491" y="1188" width="128" height="128" as="geometry" />
        </mxCell>
        <mxCell id="FF6CjetviQNnHgp1nNf3-41" value="" style="sketch=0;pointerEvents=1;shadow=0;dashed=0;html=1;strokeColor=none;fillColor=#505050;labelPosition=center;verticalLabelPosition=bottom;verticalAlign=top;outlineConnect=0;align=center;shape=mxgraph.office.devices.cell_phone_android_proportional;" vertex="1" parent="1">
          <mxGeometry x="1633" y="1276" width="50" height="81" as="geometry" />
        </mxCell>
        <mxCell id="FF6CjetviQNnHgp1nNf3-42" value="Detector de dioxido de carbono" style="rounded=0;whiteSpace=wrap;html=1;" vertex="1" parent="1">
          <mxGeometry x="1643" y="1398" width="120" height="60" as="geometry" />
        </mxCell>
        <mxCell id="FF6CjetviQNnHgp1nNf3-43" value="Detector de monóxido de carbono" style="rounded=0;whiteSpace=wrap;html=1;" vertex="1" parent="1">
          <mxGeometry x="1603" y="1498" width="120" height="60" as="geometry" />
        </mxCell>
        <mxCell id="FF6CjetviQNnHgp1nNf3-51" value="" style="shape=mxgraph.cisco.hubs_and_gateways.generic_gateway;html=1;pointerEvents=1;dashed=0;fillColor=#036897;strokeColor=#ffffff;strokeWidth=2;verticalLabelPosition=bottom;verticalAlign=top;align=center;outlineConnect=0;" vertex="1" parent="1">
          <mxGeometry x="1643" y="758" width="66" height="74" as="geometry" />
        </mxCell>
        <mxCell id="FF6CjetviQNnHgp1nNf3-52" value="" style="shape=image;html=1;verticalAlign=top;verticalLabelPosition=bottom;labelBackgroundColor=#ffffff;imageAspect=0;aspect=fixed;image=https://cdn4.iconfinder.com/data/icons/crime-and-security-24/64/7-128.png" vertex="1" parent="1">
          <mxGeometry x="1647" y="508" width="128" height="128" as="geometry" />
        </mxCell>
        <mxCell id="FF6CjetviQNnHgp1nNf3-53" value="" style="sketch=0;pointerEvents=1;shadow=0;dashed=0;html=1;strokeColor=none;fillColor=#505050;labelPosition=center;verticalLabelPosition=bottom;verticalAlign=top;outlineConnect=0;align=center;shape=mxgraph.office.devices.cell_phone_android_proportional;" vertex="1" parent="1">
          <mxGeometry x="1789" y="596" width="50" height="81" as="geometry" />
        </mxCell>
        <mxCell id="FF6CjetviQNnHgp1nNf3-54" value="Detector de dioxido de carbono" style="rounded=0;whiteSpace=wrap;html=1;" vertex="1" parent="1">
          <mxGeometry x="1543" y="658" width="120" height="60" as="geometry" />
        </mxCell>
        <mxCell id="FF6CjetviQNnHgp1nNf3-55" value="Detector de monóxido de carbono" style="rounded=0;whiteSpace=wrap;html=1;" vertex="1" parent="1">
          <mxGeometry x="1491" y="731" width="120" height="60" as="geometry" />
        </mxCell>
        <mxCell id="FF6CjetviQNnHgp1nNf3-61" value="" style="shape=mxgraph.cisco.hubs_and_gateways.generic_gateway;html=1;pointerEvents=1;dashed=0;fillColor=#036897;strokeColor=#ffffff;strokeWidth=2;verticalLabelPosition=bottom;verticalAlign=top;align=center;outlineConnect=0;" vertex="1" parent="1">
          <mxGeometry x="1093" y="724" width="66" height="74" as="geometry" />
        </mxCell>
        <mxCell id="FF6CjetviQNnHgp1nNf3-62" value="" style="shape=image;html=1;verticalAlign=top;verticalLabelPosition=bottom;labelBackgroundColor=#ffffff;imageAspect=0;aspect=fixed;image=https://cdn4.iconfinder.com/data/icons/crime-and-security-24/64/7-128.png" vertex="1" parent="1">
          <mxGeometry x="1143" y="549" width="128" height="128" as="geometry" />
        </mxCell>
        <mxCell id="FF6CjetviQNnHgp1nNf3-63" value="" style="sketch=0;pointerEvents=1;shadow=0;dashed=0;html=1;strokeColor=none;fillColor=#505050;labelPosition=center;verticalLabelPosition=bottom;verticalAlign=top;outlineConnect=0;align=center;shape=mxgraph.office.devices.cell_phone_android_proportional;" vertex="1" parent="1">
          <mxGeometry x="1243" y="673.5" width="50" height="81" as="geometry" />
        </mxCell>
        <mxCell id="FF6CjetviQNnHgp1nNf3-64" value="Detector de dioxido de carbono" style="rounded=0;whiteSpace=wrap;html=1;" vertex="1" parent="1">
          <mxGeometry x="1005" y="573" width="120" height="60" as="geometry" />
        </mxCell>
        <mxCell id="FF6CjetviQNnHgp1nNf3-65" value="Detector de monóxido de carbono" style="rounded=0;whiteSpace=wrap;html=1;" vertex="1" parent="1">
          <mxGeometry x="913" y="648" width="120" height="60" as="geometry" />
        </mxCell>
        <mxCell id="FF6CjetviQNnHgp1nNf3-70" value="" style="endArrow=none;html=1;rounded=0;" edge="1" parent="1" source="FF6CjetviQNnHgp1nNf3-61" target="FF6CjetviQNnHgp1nNf3-8">
          <mxGeometry width="50" height="50" relative="1" as="geometry">
            <mxPoint x="1603" y="1118" as="sourcePoint" />
            <mxPoint x="1653" y="1068" as="targetPoint" />
          </mxGeometry>
        </mxCell>
        <mxCell id="FF6CjetviQNnHgp1nNf3-71" value="" style="endArrow=none;html=1;rounded=0;" edge="1" parent="1" source="FF6CjetviQNnHgp1nNf3-7" target="FF6CjetviQNnHgp1nNf3-51">
          <mxGeometry width="50" height="50" relative="1" as="geometry">
            <mxPoint x="1603" y="1118" as="sourcePoint" />
            <mxPoint x="1653" y="1068" as="targetPoint" />
          </mxGeometry>
        </mxCell>
        <mxCell id="FF6CjetviQNnHgp1nNf3-72" value="" style="endArrow=none;html=1;rounded=0;" edge="1" parent="1" source="FF6CjetviQNnHgp1nNf3-39" target="FF6CjetviQNnHgp1nNf3-10">
          <mxGeometry width="50" height="50" relative="1" as="geometry">
            <mxPoint x="1603" y="1118" as="sourcePoint" />
            <mxPoint x="1653" y="1068" as="targetPoint" />
          </mxGeometry>
        </mxCell>
        <mxCell id="FF6CjetviQNnHgp1nNf3-73" value="" style="shape=mxgraph.cisco.servers.fileserver;sketch=0;html=1;pointerEvents=1;dashed=0;fillColor=#036897;strokeColor=#ffffff;strokeWidth=2;verticalLabelPosition=bottom;verticalAlign=top;align=center;outlineConnect=0;" vertex="1" parent="1">
          <mxGeometry x="890.5" y="1018" width="43" height="62" as="geometry" />
        </mxCell>
        <mxCell id="FF6CjetviQNnHgp1nNf3-74" value="" style="shape=mxgraph.cisco.servers.fileserver;sketch=0;html=1;pointerEvents=1;dashed=0;fillColor=#036897;strokeColor=#ffffff;strokeWidth=2;verticalLabelPosition=bottom;verticalAlign=top;align=center;outlineConnect=0;" vertex="1" parent="1">
          <mxGeometry x="861" y="1118" width="43" height="62" as="geometry" />
        </mxCell>
        <mxCell id="FF6CjetviQNnHgp1nNf3-75" value="" style="shape=mxgraph.cisco.servers.fileserver;sketch=0;html=1;pointerEvents=1;dashed=0;fillColor=#036897;strokeColor=#ffffff;strokeWidth=2;verticalLabelPosition=bottom;verticalAlign=top;align=center;outlineConnect=0;" vertex="1" parent="1">
          <mxGeometry x="880" y="1221" width="43" height="62" as="geometry" />
        </mxCell>
        <mxCell id="FF6CjetviQNnHgp1nNf3-76" value="" style="endArrow=none;html=1;rounded=0;" edge="1" parent="1" source="FF6CjetviQNnHgp1nNf3-9" target="FF6CjetviQNnHgp1nNf3-75">
          <mxGeometry width="50" height="50" relative="1" as="geometry">
            <mxPoint x="1603" y="1118" as="sourcePoint" />
            <mxPoint x="1653" y="1068" as="targetPoint" />
          </mxGeometry>
        </mxCell>
        <mxCell id="FF6CjetviQNnHgp1nNf3-77" value="" style="endArrow=none;html=1;rounded=0;" edge="1" parent="1" source="FF6CjetviQNnHgp1nNf3-9" target="FF6CjetviQNnHgp1nNf3-74">
          <mxGeometry width="50" height="50" relative="1" as="geometry">
            <mxPoint x="1460" y="1140" as="sourcePoint" />
            <mxPoint x="1510" y="1090" as="targetPoint" />
          </mxGeometry>
        </mxCell>
        <mxCell id="FF6CjetviQNnHgp1nNf3-78" value="" style="endArrow=none;html=1;rounded=0;" edge="1" parent="1" source="FF6CjetviQNnHgp1nNf3-9" target="FF6CjetviQNnHgp1nNf3-73">
          <mxGeometry width="50" height="50" relative="1" as="geometry">
            <mxPoint x="1623" y="1138" as="sourcePoint" />
            <mxPoint x="1673" y="1088" as="targetPoint" />
          </mxGeometry>
        </mxCell>
        <mxCell id="FF6CjetviQNnHgp1nNf3-79" value="" style="endArrow=none;dashed=1;html=1;dashPattern=1 3;strokeWidth=2;rounded=0;" edge="1" parent="1" source="FF6CjetviQNnHgp1nNf3-43" target="FF6CjetviQNnHgp1nNf3-39">
          <mxGeometry width="50" height="50" relative="1" as="geometry">
            <mxPoint x="2083" y="778" as="sourcePoint" />
            <mxPoint x="1963" y="898" as="targetPoint" />
          </mxGeometry>
        </mxCell>
        <mxCell id="FF6CjetviQNnHgp1nNf3-80" value="" style="endArrow=none;dashed=1;html=1;dashPattern=1 3;strokeWidth=2;rounded=0;" edge="1" parent="1" source="FF6CjetviQNnHgp1nNf3-42" target="FF6CjetviQNnHgp1nNf3-39">
          <mxGeometry width="50" height="50" relative="1" as="geometry">
            <mxPoint x="2093" y="788" as="sourcePoint" />
            <mxPoint x="1973" y="908" as="targetPoint" />
          </mxGeometry>
        </mxCell>
        <mxCell id="FF6CjetviQNnHgp1nNf3-81" value="" style="endArrow=none;dashed=1;html=1;dashPattern=1 3;strokeWidth=2;rounded=0;" edge="1" parent="1" source="FF6CjetviQNnHgp1nNf3-39" target="FF6CjetviQNnHgp1nNf3-41">
          <mxGeometry width="50" height="50" relative="1" as="geometry">
            <mxPoint x="2103" y="798" as="sourcePoint" />
            <mxPoint x="1983" y="918" as="targetPoint" />
          </mxGeometry>
        </mxCell>
        <mxCell id="FF6CjetviQNnHgp1nNf3-82" value="" style="endArrow=none;dashed=1;html=1;dashPattern=1 3;strokeWidth=2;rounded=0;" edge="1" parent="1" source="FF6CjetviQNnHgp1nNf3-39" target="FF6CjetviQNnHgp1nNf3-40">
          <mxGeometry width="50" height="50" relative="1" as="geometry">
            <mxPoint x="2113" y="808" as="sourcePoint" />
            <mxPoint x="1993" y="928" as="targetPoint" />
          </mxGeometry>
        </mxCell>
        <mxCell id="FF6CjetviQNnHgp1nNf3-83" value="" style="endArrow=none;dashed=1;html=1;dashPattern=1 3;strokeWidth=2;rounded=0;" edge="1" parent="1" source="FF6CjetviQNnHgp1nNf3-55" target="FF6CjetviQNnHgp1nNf3-51">
          <mxGeometry width="50" height="50" relative="1" as="geometry">
            <mxPoint x="2083" y="778" as="sourcePoint" />
            <mxPoint x="1963" y="898" as="targetPoint" />
          </mxGeometry>
        </mxCell>
        <mxCell id="FF6CjetviQNnHgp1nNf3-84" value="" style="endArrow=none;dashed=1;html=1;dashPattern=1 3;strokeWidth=2;rounded=0;" edge="1" parent="1" source="FF6CjetviQNnHgp1nNf3-53" target="FF6CjetviQNnHgp1nNf3-51">
          <mxGeometry width="50" height="50" relative="1" as="geometry">
            <mxPoint x="2093" y="788" as="sourcePoint" />
            <mxPoint x="1973" y="908" as="targetPoint" />
          </mxGeometry>
        </mxCell>
        <mxCell id="FF6CjetviQNnHgp1nNf3-85" value="" style="endArrow=none;dashed=1;html=1;dashPattern=1 3;strokeWidth=2;rounded=0;" edge="1" parent="1" source="FF6CjetviQNnHgp1nNf3-52" target="FF6CjetviQNnHgp1nNf3-51">
          <mxGeometry width="50" height="50" relative="1" as="geometry">
            <mxPoint x="2103" y="798" as="sourcePoint" />
            <mxPoint x="1983" y="918" as="targetPoint" />
          </mxGeometry>
        </mxCell>
        <mxCell id="FF6CjetviQNnHgp1nNf3-86" value="" style="endArrow=none;dashed=1;html=1;dashPattern=1 3;strokeWidth=2;rounded=0;" edge="1" parent="1" source="FF6CjetviQNnHgp1nNf3-54" target="FF6CjetviQNnHgp1nNf3-51">
          <mxGeometry width="50" height="50" relative="1" as="geometry">
            <mxPoint x="2113" y="808" as="sourcePoint" />
            <mxPoint x="1993" y="928" as="targetPoint" />
          </mxGeometry>
        </mxCell>
        <mxCell id="FF6CjetviQNnHgp1nNf3-87" value="" style="endArrow=none;dashed=1;html=1;dashPattern=1 3;strokeWidth=2;rounded=0;" edge="1" parent="1" source="FF6CjetviQNnHgp1nNf3-61" target="FF6CjetviQNnHgp1nNf3-62">
          <mxGeometry width="50" height="50" relative="1" as="geometry">
            <mxPoint x="1253" y="808" as="sourcePoint" />
            <mxPoint x="1102" y="643" as="targetPoint" />
          </mxGeometry>
        </mxCell>
        <mxCell id="FF6CjetviQNnHgp1nNf3-88" value="" style="endArrow=none;dashed=1;html=1;dashPattern=1 3;strokeWidth=2;rounded=0;" edge="1" parent="1" source="FF6CjetviQNnHgp1nNf3-61" target="FF6CjetviQNnHgp1nNf3-65">
          <mxGeometry width="50" height="50" relative="1" as="geometry">
            <mxPoint x="1263" y="818" as="sourcePoint" />
            <mxPoint x="1112" y="653" as="targetPoint" />
          </mxGeometry>
        </mxCell>
        <mxCell id="FF6CjetviQNnHgp1nNf3-89" value="" style="endArrow=none;dashed=1;html=1;dashPattern=1 3;strokeWidth=2;rounded=0;" edge="1" parent="1" source="FF6CjetviQNnHgp1nNf3-61" target="FF6CjetviQNnHgp1nNf3-63">
          <mxGeometry width="50" height="50" relative="1" as="geometry">
            <mxPoint x="1156" y="734" as="sourcePoint" />
            <mxPoint x="1182" y="687" as="targetPoint" />
          </mxGeometry>
        </mxCell>
        <mxCell id="FF6CjetviQNnHgp1nNf3-90" value="" style="ellipse;whiteSpace=wrap;html=1;aspect=fixed;fillColor=#f8cecc;strokeColor=#b85450;" vertex="1" parent="1">
          <mxGeometry x="-161" y="127.5" width="50" height="50" as="geometry" />
        </mxCell>
        <mxCell id="FF6CjetviQNnHgp1nNf3-120" value="" style="ellipse;whiteSpace=wrap;html=1;aspect=fixed;fillColor=#d5e8d4;strokeColor=#82b366;" vertex="1" parent="1">
          <mxGeometry x="-161" y="288.5" width="50" height="50" as="geometry" />
        </mxCell>
        <mxCell id="FF6CjetviQNnHgp1nNf3-121" value="" style="ellipse;whiteSpace=wrap;html=1;aspect=fixed;fillColor=#fff2cc;strokeColor=#d6b656;" vertex="1" parent="1">
          <mxGeometry x="-161" y="207.5" width="50" height="50" as="geometry" />
        </mxCell>
        <mxCell id="FF6CjetviQNnHgp1nNf3-122" value="" style="shape=mxgraph.cisco.misc.mcu;html=1;pointerEvents=1;dashed=0;fillColor=#036897;strokeColor=#ffffff;strokeWidth=2;verticalLabelPosition=bottom;verticalAlign=top;align=center;outlineConnect=0;" vertex="1" parent="1">
          <mxGeometry x="-271" y="200.5" width="56" height="64" as="geometry" />
        </mxCell>
        <mxCell id="FF6CjetviQNnHgp1nNf3-123" value="" style="shape=mxgraph.cisco.people.standing_man;sketch=0;html=1;pointerEvents=1;dashed=0;fillColor=#f8cecc;strokeColor=#b85450;strokeWidth=2;verticalLabelPosition=bottom;verticalAlign=top;align=center;outlineConnect=0;" vertex="1" parent="1">
          <mxGeometry x="-341" y="138.5" width="22" height="62" as="geometry" />
        </mxCell>
        <mxCell id="FF6CjetviQNnHgp1nNf3-124" value="" style="shape=mxgraph.cisco.people.running_man;sketch=0;html=1;pointerEvents=1;dashed=0;fillColor=#d5e8d4;strokeColor=#82b366;strokeWidth=2;verticalLabelPosition=bottom;verticalAlign=top;align=center;outlineConnect=0;" vertex="1" parent="1">
          <mxGeometry x="-360" y="246" width="60" height="70" as="geometry" />
        </mxCell>
        <mxCell id="FF6CjetviQNnHgp1nNf3-125" value="" style="endArrow=none;html=1;rounded=0;" edge="1" parent="1" source="FF6CjetviQNnHgp1nNf3-120" target="FF6CjetviQNnHgp1nNf3-122">
          <mxGeometry width="50" height="50" relative="1" as="geometry">
            <mxPoint x="-99" y="440.5" as="sourcePoint" />
            <mxPoint x="-49" y="390.5" as="targetPoint" />
          </mxGeometry>
        </mxCell>
        <mxCell id="FF6CjetviQNnHgp1nNf3-126" value="" style="endArrow=none;html=1;rounded=0;" edge="1" parent="1" source="FF6CjetviQNnHgp1nNf3-122" target="FF6CjetviQNnHgp1nNf3-123">
          <mxGeometry width="50" height="50" relative="1" as="geometry">
            <mxPoint x="-89" y="450.5" as="sourcePoint" />
            <mxPoint x="-39" y="400.5" as="targetPoint" />
          </mxGeometry>
        </mxCell>
        <mxCell id="FF6CjetviQNnHgp1nNf3-127" value="" style="endArrow=none;html=1;rounded=0;" edge="1" parent="1" source="FF6CjetviQNnHgp1nNf3-122" target="FF6CjetviQNnHgp1nNf3-124">
          <mxGeometry width="50" height="50" relative="1" as="geometry">
            <mxPoint x="-79" y="460.5" as="sourcePoint" />
            <mxPoint x="-29" y="410.5" as="targetPoint" />
          </mxGeometry>
        </mxCell>
        <mxCell id="FF6CjetviQNnHgp1nNf3-128" value="" style="endArrow=none;html=1;rounded=0;" edge="1" parent="1" source="FF6CjetviQNnHgp1nNf3-90" target="FF6CjetviQNnHgp1nNf3-122">
          <mxGeometry width="50" height="50" relative="1" as="geometry">
            <mxPoint x="-99" y="440.5" as="sourcePoint" />
            <mxPoint x="-49" y="390.5" as="targetPoint" />
          </mxGeometry>
        </mxCell>
        <mxCell id="FF6CjetviQNnHgp1nNf3-129" value="" style="endArrow=none;html=1;rounded=0;" edge="1" parent="1" source="FF6CjetviQNnHgp1nNf3-121" target="FF6CjetviQNnHgp1nNf3-122">
          <mxGeometry width="50" height="50" relative="1" as="geometry">
            <mxPoint x="-89" y="450.5" as="sourcePoint" />
            <mxPoint x="-39" y="400.5" as="targetPoint" />
          </mxGeometry>
        </mxCell>
        <mxCell id="FF6CjetviQNnHgp1nNf3-130" value="DNS" style="text;html=1;align=center;verticalAlign=middle;whiteSpace=wrap;rounded=0;" vertex="1" parent="1">
          <mxGeometry x="-60" y="347" width="60" height="30" as="geometry" />
        </mxCell>
        <mxCell id="FF6CjetviQNnHgp1nNf3-131" value="HTTP" style="text;html=1;align=center;verticalAlign=middle;whiteSpace=wrap;rounded=0;" vertex="1" parent="1">
          <mxGeometry x="-60" y="459" width="60" height="30" as="geometry" />
        </mxCell>
        <mxCell id="FF6CjetviQNnHgp1nNf3-132" value="DHCP&lt;span style=&quot;color: rgba(0, 0, 0, 0); font-family: monospace; font-size: 0px; text-align: start; text-wrap-mode: nowrap;&quot;&gt;%3CmxGraphModel%3E%3Croot%3E%3CmxCell%20id%3D%220%22%2F%3E%3CmxCell%20id%3D%221%22%20parent%3D%220%22%2F%3E%3CmxCell%20id%3D%222%22%20value%3D%22DNS%22%20style%3D%22text%3Bhtml%3D1%3Balign%3Dcenter%3BverticalAlign%3Dmiddle%3BwhiteSpace%3Dwrap%3Brounded%3D0%3B%22%20vertex%3D%221%22%20parent%3D%221%22%3E%3CmxGeometry%20x%3D%22-60%22%20y%3D%22347%22%20width%3D%2260%22%20height%3D%2230%22%20as%3D%22geometry%22%2F%3E%3C%2FmxCell%3E%3C%2Froot%3E%3C%2FmxGraphModel%3E&lt;/span&gt;" style="text;html=1;align=center;verticalAlign=middle;whiteSpace=wrap;rounded=0;" vertex="1" parent="1">
          <mxGeometry x="121.5" y="1100" width="60" height="30" as="geometry" />
        </mxCell>
        <mxCell id="FF6CjetviQNnHgp1nNf3-133" value="AAA" style="text;html=1;align=center;verticalAlign=middle;whiteSpace=wrap;rounded=0;" vertex="1" parent="1">
          <mxGeometry x="259" y="1140" width="60" height="30" as="geometry" />
        </mxCell>
        <mxCell id="FF6CjetviQNnHgp1nNf3-134" value="IOT" style="text;html=1;align=center;verticalAlign=middle;whiteSpace=wrap;rounded=0;" vertex="1" parent="1">
          <mxGeometry x="401.5" y="1100" width="60" height="30" as="geometry" />
        </mxCell>
        <mxCell id="FF6CjetviQNnHgp1nNf3-135" value="IOTGob" style="text;html=1;align=center;verticalAlign=middle;whiteSpace=wrap;rounded=0;" vertex="1" parent="1">
          <mxGeometry x="852.5" y="1180" width="60" height="30" as="geometry" />
        </mxCell>
        <mxCell id="FF6CjetviQNnHgp1nNf3-136" value="DHCPGob" style="text;html=1;align=center;verticalAlign=middle;whiteSpace=wrap;rounded=0;" vertex="1" parent="1">
          <mxGeometry x="870" y="1283" width="60" height="30" as="geometry" />
        </mxCell>
        <mxCell id="FF6CjetviQNnHgp1nNf3-137" value="Email" style="text;html=1;align=center;verticalAlign=middle;whiteSpace=wrap;rounded=0;" vertex="1" parent="1">
          <mxGeometry x="882" y="1080" width="60" height="30" as="geometry" />
        </mxCell>
        <mxCell id="FF6CjetviQNnHgp1nNf3-138" value="VPN" style="text;html=1;align=center;verticalAlign=middle;whiteSpace=wrap;rounded=0;" vertex="1" parent="1">
          <mxGeometry x="1521" y="471" width="60" height="30" as="geometry" />
        </mxCell>
        <mxCell id="FF6CjetviQNnHgp1nNf3-139" value="FileServer" style="text;html=1;align=center;verticalAlign=middle;whiteSpace=wrap;rounded=0;" vertex="1" parent="1">
          <mxGeometry x="1524.5" y="588" width="60" height="30" as="geometry" />
        </mxCell>
      </root>
    </mxGraphModel>
  </diagram>
</mxfile>
